<?xml version="1.0" encoding="latin1"?>
<EXTENSION VERSION="6.1">
<LOGICS>
<LOGICITEM NAME="DisplayStyle">
	<STATE NAME="Viewer3dDisplayStyleState" VERSION="6.1">
	<PROPERTIES>
	<PROPERTY NAME="AtomDisplayStyle">
	<VALUE>3</VALUE>
	</PROPERTY>
	</PROPERTIES>
	</STATE>
</LOGICITEM>
<LOGICITEM NAME="Labels">
	<STATE NAME="Viewer3dLabelsState" VERSION="6.1">
	<PROPERTIES>
	<PROPERTY NAME="SelectedProperties">
	<VALUE>
	<ITEM>ElementSymbol</ITEM>
	</VALUE>
	</PROPERTY>
	</PROPERTIES>
	</STATE>
</LOGICITEM>
<LOGICITEM NAME="Lighting">
	<STATE NAME="Viewer3dLightingState" VERSION="6.1">
	<PROPERTIES>
	</PROPERTIES>
	</STATE>
</LOGICITEM>
<LOGICITEM NAME="MovementOptions">
	<STATE NAME="Viewer3dMovementOptionsState" VERSION="6.1">
	<PROPERTIES>
	</PROPERTIES>
	</STATE>
</LOGICITEM>
<LOGICITEM NAME="Options">
	<STATE NAME="Viewer3dOptionsState" VERSION="6.1">
	<PROPERTIES>
	</PROPERTIES>
	</STATE>
</LOGICITEM>
<LOGICITEM NAME="Transform">
	<STATE NAME="Viewer3dTransformState" VERSION="6.1">
	<PROPERTIES>
	<PROPERTY NAME="CameraX">
	<VALUE>-1.22070857002672</VALUE>
	</PROPERTY>
	<PROPERTY NAME="CameraY">
	<VALUE>-4.523488059331491</VALUE>
	</PROPERTY>
	<PROPERTY NAME="CameraZ">
	<VALUE>11.06155745062415</VALUE>
	</PROPERTY>
	<PROPERTY NAME="ViewX">
	<VALUE>-2.560236215591431</VALUE>
	</PROPERTY>
	<PROPERTY NAME="ViewY">
	<VALUE>0.4408956170082092</VALUE>
	</PROPERTY>
	<PROPERTY NAME="ViewZ">
	<VALUE>-0.2064311504364014</VALUE>
	</PROPERTY>
	<PROPERTY NAME="UpX">
	<VALUE>0.1309918844392133</VALUE>
	</PROPERTY>
	<PROPERTY NAME="UpY">
	<VALUE>0.9128878116029174</VALUE>
	</PROPERTY>
	<PROPERTY NAME="UpZ">
	<VALUE>0.3866225156892701</VALUE>
	</PROPERTY>
	</PROPERTIES>
	</STATE>
</LOGICITEM>
</LOGICS>
</EXTENSION>
